ragpy/__init__.py
ragpy/embeddings.py
ragpy/rag_service.py
ragpy/vectorstore/__init__.py
ragpy/vectorstore/qdrant.py
ragpy-0.1.0.dist-info/METADATA
ragpy-0.1.0.dist-info/WHEEL
ragpy-0.1.0.dist-info/RECORD
