Metadata-Version: 2.4
Name: ragpy
Version: 0.1.0
Summary: Unified RAG service abstraction for vector stores like Qdrant.
Author-email: Ruslan Dev <ruslandev@uzoo.ai>
License: MIT
Requires-Python: >=3.9
Requires-Dist: numpy>=1.23
Requires-Dist: openai>=2.6.1
Requires-Dist: qdrant-client[fastembed]>=1.15.1
